{"errors":[],"warnings":[],"namedChunkGroups":{"app":{"chunks":[4,1,0],"assets":["webpack-runtime-9a013f85fa9c30a69263.js","webpack-runtime-9a013f85fa9c30a69263.js.map","commons-cc8b1397a5efb91b1e0b.js","commons-cc8b1397a5efb91b1e0b.js.map","app-3e54ad0db736f2c8f8d8.js","app-3e54ad0db736f2c8f8d8.js.map"],"children":{},"childAssets":{}},"component---src-pages-index-js":{"chunks":[3,2],"assets":["styles.b7babf6f224fff170a5a.css","styles-020b3ab4bca97621e714.js","styles-020b3ab4bca97621e714.js.map","component---src-pages-index-js-157a94d16159ed544a38.js","component---src-pages-index-js-157a94d16159ed544a38.js.map"],"children":{},"childAssets":{}}},"assetsByChunkName":{"app":["webpack-runtime-9a013f85fa9c30a69263.js","commons-cc8b1397a5efb91b1e0b.js","app-3e54ad0db736f2c8f8d8.js"],"component---src-pages-index-js":["styles.b7babf6f224fff170a5a.css","styles-020b3ab4bca97621e714.js","component---src-pages-index-js-157a94d16159ed544a38.js"]}}